metasub_utils.packet_parse-0.3.12-py3.6-nspkg.pth
metasub_utils/packet_parse/__init__.py
metasub_utils/packet_parse/metadata_ontology.py
metasub_utils/packet_parse/packet_parse.py
metasub_utils.packet_parse-0.3.12.dist-info/METADATA
metasub_utils.packet_parse-0.3.12.dist-info/WHEEL
metasub_utils.packet_parse-0.3.12.dist-info/entry_points.txt
metasub_utils.packet_parse-0.3.12.dist-info/namespace_packages.txt
metasub_utils.packet_parse-0.3.12.dist-info/top_level.txt
metasub_utils.packet_parse-0.3.12.dist-info/RECORD
