Metadata-Version: 2.1
Name: metasub-utils.packet-parse
Version: 0.3.12
Summary: UNKNOWN
Home-page: UNKNOWN
Author: David Danko
Author-email: dcdanko@gmail.com
License: MIT license
Platform: UNKNOWN
Classifier: License :: OSI Approved :: MIT License
Classifier: Natural Language :: English
Classifier: Programming Language :: Python :: 3.6
Requires-Dist: capalyzer (>=2.15.7)
Requires-Dist: pandas
